dact/__init__.py
dact/__main__.py
dact/classmodule.py
dact/createreact.py
dact/funcmodule.py
dact/mydatas.py
dact/visuals.py
dact/template_files/__init__.py
dact/template_files/css_data.py
dact/template_files/html_data.py
dact/template_files/js_data.py
dact/template_files/package_file.py
dact-1.2.3.dist-info/LICENSE
dact-1.2.3.dist-info/METADATA
dact-1.2.3.dist-info/WHEEL
dact-1.2.3.dist-info/entry_points.txt
dact-1.2.3.dist-info/top_level.txt
dact-1.2.3.dist-info/RECORD
