Metadata-Version: 2.1
Name: dact
Version: 1.2.3
Summary: UNKNOWN
Home-page: https://github.com/ayushmankumar7/dact
Author: Ayushman Kumar|Arkaprabha Chakraborty
Author-email: ayushmankumar7@gmail.com
License: UNKNOWN
Platform: UNKNOWN
Classifier: Programming Language :: Python :: 3
Classifier: Operating System :: OS Independent
Requires-Dist: django (==3.0.8)
